README
setup.py
sqlit/__init__.py
sqlit/main.py
sqlit.egg-info/PKG-INFO
sqlit.egg-info/SOURCES.txt
sqlit.egg-info/dependency_links.txt
sqlit.egg-info/entry_points.txt
sqlit.egg-info/requires.txt
sqlit.egg-info/top_level.txt