Metadata-Version: 1.0
Name: sqlit
Version: 0.1.4
Summary: Run quick queries over multiple sqlite dbs
Home-page: https://github.com/paulfitz/sqlit
Author: Paul Fitzpatrick
Author-email: paulfitz@alum.mit.edu
License: UNKNOWN
Platform: UNKNOWN
